Metadata-Version: 1.0
Name: pdemo
Version: 0.0.3
Summary: pip demo
Home-page: https://github.com/ezhonca/pdemo.git
Author: caizhongming
Author-email: zhongming.cai@foxmail.com
License: MIT Licence
Keywords: pip,pathtool,timetool,magetool,mage
Platform: any
